README.rst
setup.py
SeriesMarker.egg-info/PKG-INFO
SeriesMarker.egg-info/SOURCES.txt
SeriesMarker.egg-info/dependency_links.txt
SeriesMarker.egg-info/requires.txt
SeriesMarker.egg-info/top_level.txt
bin/seriesmarker
seriesmarker/__init__.py
seriesmarker/seriesmarker.py
seriesmarker/gui/__init__.py
seriesmarker/gui/about_dialog.py
seriesmarker/gui/main_window.py
seriesmarker/gui/search_dialog.py
seriesmarker/gui/splash_screen.py
seriesmarker/gui/model/__init__.py
seriesmarker/gui/model/decorated_node.py
seriesmarker/gui/model/episode_node.py
seriesmarker/gui/model/season_node.py
seriesmarker/gui/model/series_node.py
seriesmarker/gui/model/sort_filter_proxy_model.py
seriesmarker/gui/model/tree_node.py
seriesmarker/gui/model/tree_series_model.py
seriesmarker/gui/model/search/__init__.py
seriesmarker/gui/model/search/search_model.py
seriesmarker/gui/model/search/search_node.py
seriesmarker/gui/resources/__init__.py
seriesmarker/gui/resources/serieswatcher_rc.py
seriesmarker/gui/resources/ui_about_dialog.py
seriesmarker/gui/resources/ui_main_window.py
seriesmarker/gui/resources/ui_search_dialog.py
seriesmarker/net/__init__.py
seriesmarker/net/banner_loader.py
seriesmarker/net/tvdb.py
seriesmarker/persistence/__init__.py
seriesmarker/persistence/database.py
seriesmarker/persistence/exception.py
seriesmarker/persistence/factory/__init__.py
seriesmarker/persistence/factory/banner_factory.py
seriesmarker/persistence/factory/base_factory.py
seriesmarker/persistence/factory/episode_factory.py
seriesmarker/persistence/factory/role_factory.py
seriesmarker/persistence/factory/season_factory.py
seriesmarker/persistence/factory/series_factory.py
seriesmarker/persistence/model/__init__.py
seriesmarker/persistence/model/actor.py
seriesmarker/persistence/model/banner.py
seriesmarker/persistence/model/banner_extra.py
seriesmarker/persistence/model/director.py
seriesmarker/persistence/model/episode.py
seriesmarker/persistence/model/episode_extra.py
seriesmarker/persistence/model/genre.py
seriesmarker/persistence/model/guest.py
seriesmarker/persistence/model/role.py
seriesmarker/persistence/model/role_extra.py
seriesmarker/persistence/model/season.py
