Metadata-Version: 1.1
Name: SeriesMarker
Version: 0.1.0
Summary: A TV series browser and tracker application.
Home-page: https://toroettg.github.io/SeriesMarker
Author: Tobias Roettger
Author-email: toroettg@gmail.com
License: GNU GPLv3
Platform: any
Classifier: Development Status :: 3 - Alpha
Classifier: Environment :: X11 Applications
Classifier: Environment :: X11 Applications :: Qt
Classifier: Environment :: Win32 (MS Windows)
Classifier: Environment :: MacOS X
Classifier: Intended Audience :: End Users/Desktop
Classifier: License :: OSI Approved :: GNU General Public License v3 (GPLv3)
Classifier: Operating System :: POSIX :: Linux
Classifier: Operating System :: Microsoft :: Windows
Classifier: Operating System :: MacOS :: MacOS X
Classifier: Programming Language :: Python
Classifier: Programming Language :: Python :: 3
Classifier: Topic :: Multimedia
Classifier: Topic :: Utilities 
